mkshell/__init__.py
mkshell/cli.py
mkshell/explain.toml
mkshell/memory.py
mkshell/parser.py
mkshell/prompt.py
mkshell-0.1.0.dist-info/METADATA
mkshell-0.1.0.dist-info/WHEEL
mkshell-0.1.0.dist-info/entry_points.txt
mkshell-0.1.0.dist-info/RECORD
