Metadata-Version: 2.1
Name: mkshell
Version: 0.1.0
Summary: A tool to autogenerate pure shell CLI-like scripts easily.
Home-page: https://github.com/arnos-stuff/mkshell
Author: arnos-stuff
Author-email: mail@arnov.dev
Requires-Python: >=3.11,<4.0
Classifier: Programming Language :: Python :: 3
Classifier: Programming Language :: Python :: 3.11
Requires-Dist: addict (>=2.4.0,<3.0.0)
Requires-Dist: pyyaml (>=6.0.1,<7.0.0)
Requires-Dist: quickbar (>=0.1.0,<0.2.0)
Requires-Dist: tinydb (>=4.8.0,<5.0.0)
Requires-Dist: tqdm (>=4.65.0,<5.0.0)
Requires-Dist: typer[all] (>=0.9.0,<0.10.0)
